pymultiastar/__init__.py
pymultiastar/_core.cp311-win_amd64.pyd
pymultiastar/_core.pyi
pymultiastar/geoplanner/__init__.py
pymultiastar/geoplanner/geoplanner.py
pymultiastar/geoplanner/helper.py
pymultiastar/geoplanner/landing_selection.py
pymultiastar/geoplanner/log.py
pymultiastar/geoplanner/types.py
pymultiastar/geoplanner/util.py
pymultiastar/scripts/aclm.py
pymultiastar/scripts/log.py
pymultiastar/types.py
pymultiastar/util.py
pymultiastar/visualization/__init__.py
pymultiastar/visualization/img2d_helpers.py
pymultiastar/visualization/log.py
pymultiastar/visualization/vis3d_helpers.py
pymultiastar-0.0.10.dist-info/METADATA
pymultiastar-0.0.10.dist-info/WHEEL
pymultiastar-0.0.10.dist-info/entry_points.txt
pymultiastar-0.0.10.dist-info/licenses/LICENSE
pymultiastar-0.0.10.dist-info/RECORD
