Metadata-Version: 2.1
Name: pymultiastar
Version: 0.0.10
Summary: Multi-goal A* with cpp bindings to python
Author-Email: Jeremy Castagno <jeremybyu@gmail.com>
Classifier: License :: OSI Approved :: MIT License
Classifier: Programming Language :: Python :: 3 :: Only
Classifier: Programming Language :: Python :: 3.9
Classifier: Programming Language :: Python :: 3.10
Classifier: Programming Language :: Python :: 3.11
Requires-Python: >=3.9
Requires-Dist: numpy>=1.15
Requires-Dist: pyproj>=3.0; extra == "geo"
Requires-Dist: scipy; extra == "geo"
Requires-Dist: pytest; extra == "test"
Requires-Dist: Pillow; extra == "test"
Requires-Dist: pyproj>=3.0; extra == "test"
Requires-Dist: mkdocstrings[python]; extra == "docs"
Requires-Dist: mkdocs-autorefs>=0.3.1; extra == "docs"
Requires-Dist: pymdown-extensions>=6.3; extra == "docs"
Requires-Dist: mkdocs>=1.3; extra == "docs"
Requires-Dist: griffe>=0.27.5; extra == "docs"
Requires-Dist: python-markdown-math; extra == "docs"
Requires-Dist: mkdocs-coverage>=0.2; extra == "docs"
Requires-Dist: mkdocs-gen-files>=0.3; extra == "docs"
Requires-Dist: mkdocs-literate-nav>=0.4; extra == "docs"
Requires-Dist: mkdocs-material>=7.3; extra == "docs"
Requires-Dist: mkdocs-section-index>=0.3; extra == "docs"
Requires-Dist: mkdocstrings-python>=0.5.1; extra == "docs"
Requires-Dist: markdown-callouts>=0.2; extra == "docs"
Requires-Dist: markdown-exec>=0.5; extra == "docs"
Requires-Dist: black; extra == "dev"
Requires-Dist: open3d>=0.17; extra == "dev"
Requires-Dist: matplotlib; extra == "dev"
Requires-Dist: rich; extra == "dev"
Requires-Dist: typer; extra == "dev"
Requires-Dist: ipdb; extra == "dev"
Requires-Dist: Pillow; extra == "dev"
Requires-Dist: pandas; extra == "dev"
Requires-Dist: seaborn; extra == "dev"
Requires-Dist: pymultiastar[geo,test]; extra == "dev"
Provides-Extra: geo
Provides-Extra: test
Provides-Extra: docs
Provides-Extra: dev
